MSA_Pairformer/__init__.py
MSA_Pairformer/categorical_jacobian.py
MSA_Pairformer/chunk_layer.py
MSA_Pairformer/core.py
MSA_Pairformer/custom_typing.py
MSA_Pairformer/data_downloader.py
MSA_Pairformer/dataset.py
MSA_Pairformer/model.py
MSA_Pairformer/modules_old.py
MSA_Pairformer/outer_product.py
MSA_Pairformer/pairwise_operations.py
MSA_Pairformer/plotting.py
MSA_Pairformer/positional_encoding.py
MSA_Pairformer/regression.py
MSA_Pairformer/test.ipynb
MSA_Pairformer/training_utils.py
MSA_Pairformer/utils.py
msa_pairformer-1.0.1.dist-info/METADATA
msa_pairformer-1.0.1.dist-info/WHEEL
msa_pairformer-1.0.1.dist-info/licenses/LICENSE
msa_pairformer-1.0.1.dist-info/RECORD
