Metadata-Version: 2.4
Name: msa-pairformer
Version: 1.0.1
Summary: MSA Pairformer model repository
Author: Yo Akiyama
Maintainer-email: Yo Akiyama <yo_aki@mit.edu>
License: Modified MIT License (Coffee edition)
License-File: LICENSE
Requires-Python: >=3.10
Requires-Dist: biopython>=1.85
Requires-Dist: einops>=0.8.0
Requires-Dist: einx>=0.3.0
Requires-Dist: jaxtyping>=0.2.38
Requires-Dist: matplotlib>=3.5.1
Requires-Dist: numpy<2.0,>=1.26
Requires-Dist: scikit-learn>=0.23.2
Requires-Dist: scipy>=1.8.0
Requires-Dist: torch>=2.5.0
Requires-Dist: tqdm>=4.67.1
